{"lastUpdateDate":"2018-03-21T16:48:45.000Z","fridgeParameters":{"cooldownDate":"2017-09-07","Temperature":{"date":"2018-03-21T16:48:45Z","value":0.021,"unit":"K"}},"qubits":[{"name":"Q0","buffer":{"date":"2018-03-21T16:48:45Z","value":10,"unit":"ns"},"gateTime":{"date":"2018-03-21T16:48:45Z","value":50,"unit":"ns"},"T2":{"date":"2018-03-21T16:48:45Z","value":13.3,"unit":"µs"},"T1":{"date":"2018-03-21T16:48:45Z","value":45.7,"unit":"µs"},"frequency":{"date":"2018-03-21T16:48:45Z","value":5.24205,"unit":"GHz"},"gateError":{"date":"2018-03-21T16:48:45Z","value":0.0013737021608475342},"readoutError":{"date":"2018-03-21T16:48:45Z","value":0.055}},{"name":"Q1","buffer":{"date":"2018-03-21T16:48:45Z","value":10,"unit":"ns"},"gateTime":{"date":"2018-03-21T16:48:45Z","value":50,"unit":"ns"},"T2":{"date":"2018-03-21T16:48:45Z","value":52.5,"unit":"µs"},"T1":{"date":"2018-03-21T16:48:45Z","value":49.2,"unit":"µs"},"frequency":{"date":"2018-03-21T16:48:45Z","value":5.30741,"unit":"GHz"},"gateError":{"date":"2018-03-21T16:48:45Z","value":0.0007726307293453583},"readoutError":{"date":"2018-03-21T16:48:45Z","value":0.043}},{"name":"Q2","buffer":{"date":"2018-03-21T16:48:45Z","value":10,"unit":"ns"},"gateTime":{"date":"2018-03-21T16:48:45Z","value":50,"unit":"ns"},"T2":{"date":"2018-03-21T16:48:45Z","value":46.3,"unit":"µs"},"T1":{"date":"2018-03-21T16:48:45Z","value":34.3,"unit":"µs"},"frequency":{"date":"2018-03-21T16:48:45Z","value":5.35152,"unit":"GHz"},"gateError":{"date":"2018-03-21T16:48:45Z","value":0.0011160854878761173},"readoutError":{"date":"2018-03-21T16:48:45Z","value":0.078}},{"name":"Q4","buffer":{"date":"2018-03-21T16:48:45Z","value":10,"unit":"ns"},"gateTime":{"date":"2018-03-21T16:48:45Z","value":50,"unit":"ns"},"T2":{"date":"2018-03-21T16:48:45Z","value":29.8,"unit":"µs"},"T1":{"date":"2018-03-21T16:48:45Z","value":55.7,"unit":"µs"},"frequency":{"date":"2018-03-21T16:48:45Z","value":5.18921,"unit":"GHz"},"gateError":{"date":"2018-03-21T16:48:45Z","value":0.0012019552727863259},"readoutError":{"date":"2018-03-21T16:48:45Z","value":0.095}}],"multiQubitGates":[{"qubits":[1,0],"type":"CX","gateError":{"date":"2018-03-21T16:48:45Z","value":0.027656550643137795},"name":"CX1_0"},{"qubits":[2,0],"type":"CX","gateError":{"date":"2018-03-21T16:48:45Z","value":0.030444410051996246},"name":"CX2_0"},{"qubits":[2,1],"type":"CX","gateError":{"date":"2018-03-21T16:48:45Z","value":0.027928299887439056},"name":"CX2_1"}],"version":"3.0"}